online_store/__init__.py
online_store/__main__.py
online_store/order_management.py
online_store/user_management.py
online_store_homeworkcu-0.2.0.dist-info/METADATA
online_store_homeworkcu-0.2.0.dist-info/WHEEL
online_store_homeworkcu-0.2.0.dist-info/top_level.txt
online_store_homeworkcu-0.2.0.dist-info/RECORD
