Metadata-Version: 2.1
Name: online-store-homeworkcu
Version: 0.2.0
Summary: Исполняемый пакет для управления пользователями и заказами в онлайн-магазине
Author-email: Andrey <burovaatt@gmail.com>
License: MIT
Requires-Python: >=3.8
